missinglink/__init__.py
missinglink/core/__init__.py
missinglink/core/api.py
missinglink/core/avro_utils.py
missinglink/core/bounded_logger.py
missinglink/core/config.py
missinglink/core/context.py
missinglink/core/default_params.py
missinglink/core/eprint.py
missinglink/core/exceptions.py
missinglink/core/json_utils.py
missinglink/core/multi_process_control.py
missinglink/core/print_status.py
missinglink/core/update_timer.py
missinglink/core/utils/__init__.py
missinglink/core/utils/file_utils.py
missinglink/core/utils/os_utils.py
ml_core-19.9.3999.dist-info/METADATA
ml_core-19.9.3999.dist-info/WHEEL
ml_core-19.9.3999.dist-info/top_level.txt
ml_core-19.9.3999.dist-info/RECORD
