Metadata-Version: 2.1
Name: ml-core
Version: 19.9.3999
Summary: Core Package for MissingLink.ai
Home-page: https://missinglink.ai
Author: missinglink.ai
Author-email: support@missinglink.ai
License: Apache
Platform: UNKNOWN
Classifier: Development Status :: 4 - Beta
Classifier: Intended Audience :: Developers
Classifier: License :: OSI Approved :: Apache Software License
Classifier: Programming Language :: Python
Classifier: Programming Language :: Python :: 3
Classifier: Programming Language :: Python :: 2.7
Requires-Dist: requests (~=2.18)
Requires-Dist: retrying (~=1.3)
Requires-Dist: six (~=1.11)
Requires-Dist: pyjwt (~=1.5)
Requires-Dist: avro ; python_version<"3.0"
Requires-Dist: avro-python3 ; python_version>"3.0"
